{
	"configurations" : 
	[
		{
			"directories" : 
			[
				{
					"build" : ".",
					"jsonFile" : "directory-.-Debug-d0094a50bb2071803777.json",
					"minimumCMakeVersion" : 
					{
						"string" : "3.21"
					},
					"projectIndex" : 0,
					"source" : ".",
					"targetIndexes" : 
					[
						0
					]
				}
			],
			"name" : "Debug",
			"projects" : 
			[
				{
					"directoryIndexes" : 
					[
						0
					],
					"name" : "teste_01",
					"targetIndexes" : 
					[
						0
					]
				}
			],
			"targets" : 
			[
				{
					"directoryIndex" : 0,
					"id" : "teste_01::@6890427a1f51a3e7e1df",
					"jsonFile" : "target-teste_01-Debug-3e6ec75678ceb88c7d88.json",
					"name" : "teste_01",
					"projectIndex" : 0
				}
			]
		}
	],
	"kind" : "codemodel",
	"paths" : 
	{
		"build" : "C:/VSCode/Aula_Lab_prog_02/Aula_11_teste/teste_01/cmake-build-debug",
		"source" : "C:/VSCode/Aula_Lab_prog_02/Aula_11_teste/teste_01"
	},
	"version" : 
	{
		"major" : 2,
		"minor" : 3
	}
}
